nx/__init__.py
nx/__main__.py
nx/db.py
nx/exceptions.py
nx/initialize.py
nx/logging.py
nx/py.typed
nx/redis.py
nx/version.py
nx/config/__init__.py
nx/config/config_model.py
nx/config/fields.py
nx/ffmpeg/__init__.py
nx/ffmpeg/ffmpeg.py
nx/ffmpeg/ffprobe.py
nx/server/__init__.py
nx/server/app.py
nx/server/bubblewrap.py
nx/server/gatekeeper.py
nx/server/lifespan.py
nx/utils/__init__.py
nx/utils/coalesce.py
nx/utils/slugify.py
nx/utils/utils.py
nx_framework-0.0.7.dist-info/licenses/LICENSE
nx_framework-0.0.7.dist-info/METADATA
nx_framework-0.0.7.dist-info/WHEEL
nx_framework-0.0.7.dist-info/top_level.txt
nx_framework-0.0.7.dist-info/RECORD
