Metadata-Version: 2.4
Name: nx-framework
Version: 0.0.7
Summary: Low-level FastAPI, asyncpg and Redis framework used by Nebula Broadcast and other projects.
Author-email: Martin Wacker <martas@imm.cz>
License-Expression: MIT
Requires-Python: >=3.12
License-File: LICENSE
Requires-Dist: aiofiles>=24.1.0
Requires-Dist: aioshutil>=1.5
Requires-Dist: asyncpg>=0.30.0
Requires-Dist: fastapi>=0.115.8
Requires-Dist: loguru>=0.7.3
Requires-Dist: pydantic-settings>=2.7.1
Requires-Dist: pydantic[email]>=2.10.6
Requires-Dist: python-dotenv>=1.0.1
Requires-Dist: redis>=5.2.1
Requires-Dist: shortuuid>=1.0.13
Requires-Dist: unidecode>=1.3.8
Dynamic: license-file
